dilldb/__init__.py
dilldb/dilldb.py
dilldb/key_string_error.py
dilldb-0.1.1.dist-info/LICENSE
dilldb-0.1.1.dist-info/METADATA
dilldb-0.1.1.dist-info/WHEEL
dilldb-0.1.1.dist-info/top_level.txt
dilldb-0.1.1.dist-info/RECORD
